pydag/__init__.py
pydag/dag.py
pydag/node.py
pydag-0.0.1.dist-info/WHEEL
pydag-0.0.1.dist-info/METADATA
pydag-0.0.1.dist-info/RECORD
