Metadata-Version: 2.1
Name: pydag
Version: 0.0.1
Summary: Python Directed Acyclic Graph
License: Apache-2.0
Author: kelvins
Author-email: kelvinpfw@gmail.com
Requires-Python: >=3.6,<4.0
Classifier: License :: OSI Approved :: Apache Software License
Classifier: Programming Language :: Python :: 3
Classifier: Programming Language :: Python :: 3.6
Classifier: Programming Language :: Python :: 3.7
Classifier: Programming Language :: Python :: 3.8
